vanilla_knn/knn.py
vanilla_knn-0.1.1.dist-info/METADATA
vanilla_knn-0.1.1.dist-info/WHEEL
vanilla_knn-0.1.1.dist-info/top_level.txt
vanilla_knn-0.1.1.dist-info/RECORD
