Metadata-Version: 2.1
Name: vanilla-knn
Version: 0.1.1
Summary: Uma implementação simples do algoritmo KNN em Python.
Home-page: https://github.com/RayVilaca/vanilla-knn
Author: RayVil
License: UNKNOWN
Platform: UNKNOWN
Classifier: Programming Language :: Python :: 3
Classifier: Operating System :: OS Independent
